nodriver/__init__.py
nodriver/cdp/README.md
nodriver/cdp/__init__.py
nodriver/cdp/accessibility.py
nodriver/cdp/animation.py
nodriver/cdp/audits.py
nodriver/cdp/autofill.py
nodriver/cdp/background_service.py
nodriver/cdp/bluetooth_emulation.py
nodriver/cdp/browser.py
nodriver/cdp/cache_storage.py
nodriver/cdp/cast.py
nodriver/cdp/console.py
nodriver/cdp/css.py
nodriver/cdp/database.py
nodriver/cdp/debugger.py
nodriver/cdp/device_access.py
nodriver/cdp/device_orientation.py
nodriver/cdp/dom.py
nodriver/cdp/dom_debugger.py
nodriver/cdp/dom_snapshot.py
nodriver/cdp/dom_storage.py
nodriver/cdp/emulation.py
nodriver/cdp/event_breakpoints.py
nodriver/cdp/extensions.py
nodriver/cdp/fed_cm.py
nodriver/cdp/fetch.py
nodriver/cdp/file_system.py
nodriver/cdp/headless_experimental.py
nodriver/cdp/heap_profiler.py
nodriver/cdp/indexed_db.py
nodriver/cdp/input_.py
nodriver/cdp/inspector.py
nodriver/cdp/io.py
nodriver/cdp/layer_tree.py
nodriver/cdp/log.py
nodriver/cdp/media.py
nodriver/cdp/memory.py
nodriver/cdp/network.py
nodriver/cdp/overlay.py
nodriver/cdp/page.py
nodriver/cdp/performance.py
nodriver/cdp/performance_timeline.py
nodriver/cdp/preload.py
nodriver/cdp/profiler.py
nodriver/cdp/pwa.py
nodriver/cdp/py.typed
nodriver/cdp/runtime.py
nodriver/cdp/schema.py
nodriver/cdp/security.py
nodriver/cdp/service_worker.py
nodriver/cdp/storage.py
nodriver/cdp/system_info.py
nodriver/cdp/target.py
nodriver/cdp/tethering.py
nodriver/cdp/tracing.py
nodriver/cdp/util.py
nodriver/cdp/web_audio.py
nodriver/cdp/web_authn.py
nodriver/core/_contradict.py
nodriver/core/browser.py
nodriver/core/config.py
nodriver/core/connection.py
nodriver/core/element.py
nodriver/core/tab.py
nodriver/core/util.py
nodriver-0.46.2.dist-info/licenses/LICENSE.txt
nodriver-0.46.2.dist-info/METADATA
nodriver-0.46.2.dist-info/WHEEL
nodriver-0.46.2.dist-info/top_level.txt
nodriver-0.46.2.dist-info/RECORD
