Metadata-Version: 2.4
Name: nodriver
Version: 0.46.2
Summary: [Docs here](https://ultrafunkamsterdam.github.io/nodriver)
Author-email: UltrafunkAmsterdam <doesnotexist@ultrafunk.nl>
Maintainer-email: UltrafunkAmsterdam <doesnotexist@ultrafunk.nl>
License:                     GNU AFFERO GENERAL PUBLIC LICENSE
Project-URL: Homepage, https://github.com/UltrafunkAmsterdam/nodriver
Project-URL: Bug Reports, https://github.com/UltrafunkAmsterdam/nodriver/issues
Project-URL: Source, https://github.com/UltrafunkAmsterdam/nodriver
Keywords: webdriver,browser,captcha,scraping,selenium,navigator,python3,cloudflare,chromedriver,anti-bot,bot-detection,cloudflare-bypass,distil,anti-detection
Classifier: Development Status :: 3 - Alpha
Classifier: Intended Audience :: Developers
Classifier: Topic :: Internet :: WWW/HTTP :: Browsers
Classifier: Programming Language :: Python :: 3.7
Classifier: Programming Language :: Python :: 3.8
Classifier: Programming Language :: Python :: 3.9
Classifier: Programming Language :: Python :: 3.10
Classifier: Programming Language :: Python :: 3.11
Classifier: Programming Language :: Python :: 3.12
Classifier: Programming Language :: Python :: 3.13
Requires-Python: >=3.9
License-File: LICENSE.txt
Requires-Dist: mss
Requires-Dist: websockets>=14
Requires-Dist: deprecated
Provides-Extra: dev
Requires-Dist: black; extra == "dev"
Requires-Dist: build; extra == "dev"
Requires-Dist: isort; extra == "dev"
Requires-Dist: sphinx; extra == "dev"
Requires-Dist: sphinx_markdown_builder; extra == "dev"
Requires-Dist: sphinx_autodoc_typehints; extra == "dev"
Requires-Dist: furo; extra == "dev"
Requires-Dist: pygments; extra == "dev"
Requires-Dist: sphinxcontrib-video; extra == "dev"
Dynamic: license-file
